{
   "s":"The ,The People's ,God's ,The Wrathful ,The Evil ,The Immortal ",
   "m":"Democratic ,Holy ,Industrial ,Bold ,Steadfast ,Righteous ,Glorious ,Shining ",
   "A":"Freedom ,Austere ,True ,Linear ,National ,Unified ,Democratic ,Royal ,Social ,Progressive ,Popular ,Republican ,Federal ,Liberty ,Homeland ,Conservative ,Liberal ,Victory ,Black ,White ,Red ,Green ,Blue ,Yellow ,Scarlet ,Emerald ,Cyan ,Amber ,Purple ,Crimson ,Grey ,Orange ,Bronze ,Silver ,Gold ,Steel ,Iron ,Northern ,Southern ,Western ,Eastern ,Ascendant ,Upward ",
   "e":"Alliance ,Clan ,Combine ,Group ,Pact ,Society ,Sodality ,Union ,Unity ,Legion ,Empire ",
   "rules":"$60s_$m_$20A_$e,$60s_$m_$20A_$e"
}
